settings.py
htmlparsingbs4based/__init__.py
htmlparsingbs4based/html_parsing/__init__.py
htmlparsingbs4based/html_parsing/html_.py
htmlparsingbs4based/html_parsing/html_parser_custombs4_script.py
htmlparsingbs4based/html_parsing/html_parsing_custombs4.py
htmlparsingbs4based/html_parsing/html2text_cp/__init__.py
htmlparsingbs4based/html_parsing/html2text_cp/__main__.py
htmlparsingbs4based/html_parsing/html2text_cp/cli.py
htmlparsingbs4based/html_parsing/html2text_cp/config.py
htmlparsingbs4based/html_parsing/html2text_cp/config_bp.py
htmlparsingbs4based/html_parsing/html2text_cp/elements.py
htmlparsingbs4based/html_parsing/html2text_cp/typing.py
htmlparsingbs4based/html_parsing/html2text_cp/utils.py
htmlparsingbs4based/html_parsing/inscriptis_cp/__init__.py
htmlparsingbs4based/html_parsing/inscriptis_cp/css_profiles.py
htmlparsingbs4based/html_parsing/inscriptis_cp/html_engine.py
htmlparsingbs4based/html_parsing/inscriptis_cp/html_properties.py
htmlparsingbs4based/html_parsing/inscriptis_cp/metadata.py
htmlparsingbs4based/html_parsing/inscriptis_cp/annotation/__init__.py
htmlparsingbs4based/html_parsing/inscriptis_cp/annotation/parser.py
htmlparsingbs4based/html_parsing/inscriptis_cp/annotation/output/__init__.py
htmlparsingbs4based/html_parsing/inscriptis_cp/annotation/output/html.py
htmlparsingbs4based/html_parsing/inscriptis_cp/annotation/output/surface.py
htmlparsingbs4based/html_parsing/inscriptis_cp/annotation/output/xml.py
htmlparsingbs4based/html_parsing/inscriptis_cp/model/__init__.py
htmlparsingbs4based/html_parsing/inscriptis_cp/model/attribute.py
htmlparsingbs4based/html_parsing/inscriptis_cp/model/config.py
htmlparsingbs4based/html_parsing/inscriptis_cp/model/css.py
htmlparsingbs4based/html_parsing/inscriptis_cp/model/html_element.py
htmlparsingbs4based/html_parsing/inscriptis_cp/model/table.py
htmlparsingbs4based/html_parsing/inscriptis_cp/model/canvas/__init__.py
htmlparsingbs4based/html_parsing/inscriptis_cp/model/canvas/block.py
htmlparsingbs4based-1.1.0.dist-info/METADATA
htmlparsingbs4based-1.1.0.dist-info/WHEEL
htmlparsingbs4based-1.1.0.dist-info/entry_points.txt
htmlparsingbs4based-1.1.0.dist-info/top_level.txt
htmlparsingbs4based-1.1.0.dist-info/RECORD
