Metadata-Version: 2.1
Name: htmlparsingbs4based
Version: 1.1.0
Summary: This package extracts/parses information from source HTML.
Home-page: https://finquest.com/
Author: Yaxiong Yuan
Author-email: yaxiong.yuan@finquest.com
Classifier: Programming Language :: Python :: 3
Classifier: License :: OSI Approved :: MIT License
Classifier: Operating System :: OS Independent
Requires-Python: >=3.8
Requires-Dist: beautifulsoup4 (==4.11.1)
Requires-Dist: json-lines (==0.5.0)
Requires-Dist: pandas (==1.5.0)
Requires-Dist: scrapy (==1.8.0)
Requires-Dist: scrapy-fake-useragent (==1.2.0)
Requires-Dist: tqdm (>=4.50.2)
Requires-Dist: retry (==0.9.2)
Requires-Dist: cryptography (>=3.2)
Requires-Dist: spacy (==3.2)
Requires-Dist: boto3 (==1.21.35)
Requires-Dist: cleanco (==2.2)
Requires-Dist: bson (==0.5.10)
Requires-Dist: pymongo (==4.3.2)
Requires-Dist: elasticsearch (==8.4.3)
Requires-Dist: openpyxl (==3.0.10)
Requires-Dist: pika (==1.3.1)
Requires-Dist: jsonlines (==3.1.0)
